hastebiny/__init__.py
hastebiny/hb.py
hastebiny-0.0.6.dist-info/LICENSE
hastebiny-0.0.6.dist-info/METADATA
hastebiny-0.0.6.dist-info/WHEEL
hastebiny-0.0.6.dist-info/top_level.txt
hastebiny-0.0.6.dist-info/RECORD
