Metadata-Version: 2.1
Name: hastebiny
Version: 0.0.6
Summary: An unofficial hastebin module.
Home-page: https://github.com/NYPDK/hastebiny
Author: BQJ
Author-email: hawkafreeman@gmail.com
License: UNKNOWN
Project-URL: Bug Tracker, https://github.com/NYPDK/hastebiny/issues
Platform: UNKNOWN
Classifier: Programming Language :: Python :: 3
Classifier: License :: OSI Approved :: MIT License
Classifier: Operating System :: OS Independent
Requires-Python: >=3.6
License-File: LICENSE
